README.md
setup.py
pulumi_rediscloud/__init__.py
pulumi_rediscloud/_inputs.py
pulumi_rediscloud/_utilities.py
pulumi_rediscloud/acl_role.py
pulumi_rediscloud/acl_rule.py
pulumi_rediscloud/acl_user.py
pulumi_rediscloud/active_active_subscription.py
pulumi_rediscloud/active_active_subscription_database.py
pulumi_rediscloud/active_active_subscription_peering.py
pulumi_rediscloud/active_active_subscription_regions.py
pulumi_rediscloud/cloud_account.py
pulumi_rediscloud/get_acl_role.py
pulumi_rediscloud/get_acl_rule.py
pulumi_rediscloud/get_acl_user.py
pulumi_rediscloud/get_cloud_account.py
pulumi_rediscloud/get_data_persistence.py
pulumi_rediscloud/get_database.py
pulumi_rediscloud/get_database_modules.py
pulumi_rediscloud/get_payment_method.py
pulumi_rediscloud/get_regions.py
pulumi_rediscloud/get_subscription.py
pulumi_rediscloud/get_subscription_peerings.py
pulumi_rediscloud/outputs.py
pulumi_rediscloud/provider.py
pulumi_rediscloud/pulumi-plugin.json
pulumi_rediscloud/py.typed
pulumi_rediscloud/subscription.py
pulumi_rediscloud/subscription_database.py
pulumi_rediscloud/subscription_peering.py
pulumi_rediscloud.egg-info/PKG-INFO
pulumi_rediscloud.egg-info/SOURCES.txt
pulumi_rediscloud.egg-info/dependency_links.txt
pulumi_rediscloud.egg-info/not-zip-safe
pulumi_rediscloud.egg-info/requires.txt
pulumi_rediscloud.egg-info/top_level.txt
pulumi_rediscloud/config/__init__.py
pulumi_rediscloud/config/vars.py