Metadata-Version: 2.1
Name: pulumi-rediscloud
Version: 1.3.1
Summary: A Pulumi package for creating and managing rediscloud cloud resources.
Home-page: https://www.pulumi.com
License: Apache-2.0
Project-URL: Repository, https://github.com/RedisLabs/pulumi-rediscloud
Keywords: pulumi rediscloud category/cloud
Platform: UNKNOWN
Requires-Python: >=3.7
